fade2/__init__.py
fade2-1.0.1.dist-info/METADATA
fade2-1.0.1.dist-info/WHEEL
fade2-1.0.1.dist-info/top_level.txt
fade2-1.0.1.dist-info/RECORD
