Metadata-Version: 2.4
Name: fade2
Version: 1.0.1
Summary: A sequence to venaxyt's fade project, with more features.
Home-page: https://github.com/qrexpy/fade2
Author: Qrexxed
License: MIT
Keywords: fade ascii art color gradient
Classifier: Development Status :: 4 - Beta
Classifier: Intended Audience :: Developers
Classifier: Operating System :: OS Independent
Classifier: License :: OSI Approved :: MIT License
Classifier: Programming Language :: Python :: 3.10
Classifier: Topic :: Terminals
Dynamic: author
Dynamic: classifier
Dynamic: description
Dynamic: description-content-type
Dynamic: home-page
Dynamic: keywords
Dynamic: license
Dynamic: summary
